README.rst
setup.py
myjscss/__init__.py
myjscss/myjscss.py
myjscss.egg-info/PKG-INFO
myjscss.egg-info/SOURCES.txt
myjscss.egg-info/dependency_links.txt
myjscss.egg-info/requires.txt
myjscss.egg-info/top_level.txt
myjscss.egg-info/zip-safe