Metadata-Version: 1.1
Name: myjscss
Version: 1.0.6
Summary: this is a  package for package combine compress cache js,css to different client lib
Home-page: http://pypi.python.org
Author: Tangrongjian
Author-email: trj_2001@sina.com
License: MIT
Keywords: combine compress cache js css
Platform: UNKNOWN
Classifier: License :: OSI Approved :: MIT License
Classifier: Programming Language :: Python
Classifier: Intended Audience :: Developers
Classifier: Operating System :: OS Independent
